setup.py
saurabhrajratan_distributions/Binomialdistribution.py
saurabhrajratan_distributions/Gaussiandistribution.py
saurabhrajratan_distributions/Generaldistribution.py
saurabhrajratan_distributions/__init__.py
saurabhrajratan_distributions.egg-info/PKG-INFO
saurabhrajratan_distributions.egg-info/SOURCES.txt
saurabhrajratan_distributions.egg-info/dependency_links.txt
saurabhrajratan_distributions.egg-info/not-zip-safe
saurabhrajratan_distributions.egg-info/top_level.txt