Metadata-Version: 1.0
Name: saurabhrajratan-distributions
Version: 0.1
Summary: Gaussian Distributions, Binomial Distributions, Mean, Variance, and Standard Deviation of Statistics
Home-page: UNKNOWN
Author: Saurabh Raj Ratan
Author-email: saurabhrajratan@gmail.com
License: UNKNOWN
Platform: UNKNOWN
